choppr/__init__.py
choppr/choppr.py
choppr/cli.py
choppr/constants.py
choppr/context.py
choppr/decorators.py
choppr/py.typed
choppr/strace.py
choppr/apt_api/__init__.py
choppr/apt_api/_utils.py
choppr/apt_api/binary_package.py
choppr/apt_api/dependency.py
choppr/apt_api/packages_file.py
choppr/apt_api/py.typed
choppr/apt_api/release_file.py
choppr/apt_api/repository.py
choppr/apt_api/sources.py
choppr/component_handlers/__init__.py
choppr/component_handlers/deb_handler.py
choppr/component_handlers/purl_handler.py
choppr/component_handlers/py.typed
choppr/component_handlers/rpm_handler.py
choppr/types/__init__.py
choppr/types/configuration.py
choppr/types/deb_package_data.py
choppr/types/enums.py
choppr/types/package_data.py
choppr/types/py.typed
choppr/types/rpm_package_data.py
choppr/types/shares.py
choppr/utils/__init__.py
choppr/utils/components.py
choppr/utils/files.py
choppr/utils/http.py
choppr/utils/logging.py
choppr/utils/py.typed
choppr/utils/strings.py
choppr-1.2.0.dist-info/METADATA
choppr-1.2.0.dist-info/WHEEL
choppr-1.2.0.dist-info/entry_points.txt
choppr-1.2.0.dist-info/licenses/LICENSE
choppr-1.2.0.dist-info/RECORD
