Metadata-Version: 2.4
Name: choppr
Version: 1.2.0
Summary: Choppr is a plugin that is meant to reduce the size of a software's Software Bill of Materials (SBOM).
Project-URL: homepage, https://hoppr.dev/
Project-URL: documentation, https://gitlab.com/hoppr/choppr/-/wikis/home
Project-URL: repository, https://gitlab.com/hoppr/choppr
Author-email: LMCO Open Source <open.source@lmco.com>
License-Expression: MIT
License-File: LICENSE
Classifier: Development Status :: 3 - Alpha
Classifier: Intended Audience :: Developers
Classifier: Intended Audience :: Information Technology
Classifier: Intended Audience :: System Administrators
Classifier: License :: OSI Approved :: MIT License
Classifier: Programming Language :: Python
Classifier: Programming Language :: Python :: 3
Classifier: Programming Language :: Python :: 3.10
Classifier: Programming Language :: Python :: 3.11
Classifier: Programming Language :: Python :: 3.12
Classifier: Topic :: Communications :: File Sharing
Classifier: Topic :: Security
Classifier: Topic :: Software Development :: Version Control
Classifier: Topic :: System :: Archiving :: Packaging
Classifier: Topic :: System :: Software Distribution
Classifier: Typing :: Typed
Requires-Python: <4,>=3.10.0
Requires-Dist: cyclonedx-python-lib>=11.1.0
Requires-Dist: jmespath<2,>=1.0.1
Requires-Dist: pydantic-yaml>=1.6.0
Requires-Dist: pydantic<3,>=2
Requires-Dist: python-debian<2,>=1.0.0
Requires-Dist: requests>=2.32.5
Requires-Dist: typer>=0.16.0
Requires-Dist: xmltodict<0.15,>=0.14.0
Requires-Dist: zstandard<0.24,>=0.23.0
